yarub/__init__.py
yarub-0.1.0.dist-info/LICENCE.txt
yarub-0.1.0.dist-info/METADATA
yarub-0.1.0.dist-info/WHEEL
yarub-0.1.0.dist-info/top_level.txt
yarub-0.1.0.dist-info/RECORD
