Metadata-Version: 2.1
Name: yarub
Version: 0.1.0
Summary: This is code with Modern standard arabic training dataset
Home-page: UNKNOWN
Author: Omdena
Author-email: almastanul@gmail.com
License: MIT
Keywords: Arabic Training dataset
Platform: UNKNOWN
Classifier: Development Status :: 5 - Production/Stable
Classifier: Intended Audience :: Education
Classifier: Operating System :: Microsoft :: Windows :: Windows 10
Classifier: License :: OSI Approved :: MIT License
Classifier: Programming Language :: Python :: 3
License-File: LICENCE.txt
